odoo/addons/hr_dms_field/README.rst
odoo/addons/hr_dms_field/__init__.py
odoo/addons/hr_dms_field/__manifest__.py
odoo/addons/hr_dms_field/demo/dms_data.xml
odoo/addons/hr_dms_field/i18n/es.po
odoo/addons/hr_dms_field/i18n/hr_dms_field.pot
odoo/addons/hr_dms_field/i18n/it.po
odoo/addons/hr_dms_field/models/__init__.py
odoo/addons/hr_dms_field/models/hr_employee.py
odoo/addons/hr_dms_field/models/hr_employee_public.py
odoo/addons/hr_dms_field/models/res_config_settings.py
odoo/addons/hr_dms_field/readme/CONFIGURE.md
odoo/addons/hr_dms_field/readme/CONTRIBUTORS.md
odoo/addons/hr_dms_field/readme/DESCRIPTION.md
odoo/addons/hr_dms_field/readme/USAGE.md
odoo/addons/hr_dms_field/security/security.xml
odoo/addons/hr_dms_field/static/description/icon.png
odoo/addons/hr_dms_field/static/description/index.html
odoo/addons/hr_dms_field/static/src/js/base/dms_list_controller.esm.js
odoo/addons/hr_dms_field/tests/__init__.py
odoo/addons/hr_dms_field/tests/test_hr_dms_field.py
odoo/addons/hr_dms_field/views/hr_employee_view.xml
odoo/addons/hr_dms_field/views/res_config_settings_view.xml
odoo_addon_hr_dms_field-18.0.1.0.0.2.dist-info/METADATA
odoo_addon_hr_dms_field-18.0.1.0.0.2.dist-info/WHEEL
odoo_addon_hr_dms_field-18.0.1.0.0.2.dist-info/top_level.txt
odoo_addon_hr_dms_field-18.0.1.0.0.2.dist-info/RECORD
